niceapp/__init__.py
niceapp-0.0.0.dist-info/METADATA
niceapp-0.0.0.dist-info/WHEEL
niceapp-0.0.0.dist-info/RECORD
