Metadata-Version: 2.1
Name: niceapp
Version: 0.0.0
Summary: Wrappers to make NiceGUI a single page app
License: MIT
Author: CJ Lazell
Author-email: cjlazell@gmail.com
Requires-Python: >=3.7,<4.0
Classifier: License :: OSI Approved :: MIT License
Classifier: Programming Language :: Python :: 3
Classifier: Programming Language :: Python :: 3.7
Classifier: Programming Language :: Python :: 3.8
Classifier: Programming Language :: Python :: 3.9
Classifier: Programming Language :: Python :: 3.10
Classifier: Programming Language :: Python :: 3.11
Requires-Dist: nicegui (>=1.2.9)
